[
  {
    "Hostname": "BOYO-A05-AS-02",
    "ActualHostname": "BOYO-A05-AS-02",
    "Site": "BOYO",
    "FileHash": "5fb6c30962bd7576648d5ef71cbf9e36b52f302dec974de3e6e2063052e953fb",
    "SourceLength": 5356,
    "SourceTimestampUtc": "2025-12-23T13:33:24.4762855Z",
    "LastIngestedUtc": "2025-12-23T13:33:32.9536638Z"
  },
  {
    "Hostname": "BOYO-A05-AS-05",
    "ActualHostname": "BOYO-A05-AS-05",
    "Site": "BOYO",
    "FileHash": "941f4de88acdfc03511d449d49ad381a762f78bfad414eaf749dbca313cc7b7b",
    "SourceLength": 5356,
    "SourceTimestampUtc": "2025-12-23T13:33:24.5192897Z",
    "LastIngestedUtc": "2025-12-23T13:33:33.2820271Z"
  },
  {
    "Hostname": "BOYO-A05-AS-12",
    "ActualHostname": "BOYO-A05-AS-12",
    "Site": "BOYO",
    "FileHash": "fcef86b7243d31337933a8adefa7af941252294802976e3be12be42a4d7521f9",
    "SourceLength": 5356,
    "SourceTimestampUtc": "2025-12-23T13:33:24.5581792Z",
    "LastIngestedUtc": "2025-12-23T13:33:33.5573666Z"
  },
  {
    "Hostname": "BOYO-A05-AS-15",
    "ActualHostname": "BOYO-A05-AS-15",
    "Site": "BOYO",
    "FileHash": "8c2422e4959d397bf57b2bdb4fcd0b9994f66cd3b4530848c2786549174ad785",
    "SourceLength": 5356,
    "SourceTimestampUtc": "2025-12-23T13:33:24.5922674Z",
    "LastIngestedUtc": "2025-12-23T13:33:33.8805514Z"
  },
  {
    "Hostname": "BOYO-A05-AS-22",
    "ActualHostname": "BOYO-A05-AS-22",
    "Site": "BOYO",
    "FileHash": "2f5c8822225f4cfeee56b7614122d2a63c2ad2ad4f2905c1b5808537a0ffbb63",
    "SourceLength": 5356,
    "SourceTimestampUtc": "2025-12-23T13:33:24.6349027Z",
    "LastIngestedUtc": "2025-12-23T13:33:34.090391Z"
  },
  {
    "Hostname": "BOYO-A05-AS-25",
    "ActualHostname": "BOYO-A05-AS-25",
    "Site": "BOYO",
    "FileHash": "cf13b2067a18434276c8c33f42b2696a810452e06923429b7bb0c81594b363fa",
    "SourceLength": 5356,
    "SourceTimestampUtc": "2025-12-23T13:33:24.6732602Z",
    "LastIngestedUtc": "2025-12-23T13:33:34.2445597Z"
  },
  {
    "Hostname": "BOYO-A05-AS-32",
    "ActualHostname": "BOYO-A05-AS-32",
    "Site": "BOYO",
    "FileHash": "dc894adbfdb4b559ed26ba46e4fdd43223a098382f8ebf0814ba225fc6f4f9ee",
    "SourceLength": 5356,
    "SourceTimestampUtc": "2025-12-23T13:33:24.6985313Z",
    "LastIngestedUtc": "2025-12-23T13:33:34.4106327Z"
  },
  {
    "Hostname": "BOYO-A05-AS-35",
    "ActualHostname": "BOYO-A05-AS-35",
    "Site": "BOYO",
    "FileHash": "c5c4a8285c96c0a23819c47617d0cce981959c47cd6a7d32a40ed18dcdc75bde",
    "SourceLength": 5356,
    "SourceTimestampUtc": "2025-12-23T13:33:24.7261726Z",
    "LastIngestedUtc": "2025-12-23T13:33:34.6213674Z"
  },
  {
    "Hostname": "BOYO-A05-AS-42",
    "ActualHostname": "BOYO-A05-AS-42",
    "Site": "BOYO",
    "FileHash": "910a13e050304698ef892298af4724313fbf393370f1a943e365482575d3242b",
    "SourceLength": 5356,
    "SourceTimestampUtc": "2025-12-23T13:33:24.3280626Z",
    "LastIngestedUtc": "2025-12-23T13:33:34.834241Z"
  },
  {
    "Hostname": "BOYO-A05-AS-45",
    "ActualHostname": "BOYO-A05-AS-45",
    "Site": "BOYO",
    "FileHash": "0e6efb02eb197c5182d347a6063966a91c9489c2feb9a54cbd00f4664a904121",
    "SourceLength": 5356,
    "SourceTimestampUtc": "2025-12-23T13:33:24.7652881Z",
    "LastIngestedUtc": "2025-12-23T13:33:34.9431674Z"
  },
  {
    "Hostname": "BOYO-A05-AS-52",
    "ActualHostname": "BOYO-A05-AS-52",
    "Site": "BOYO",
    "FileHash": "3e69b08118c43b1b4a65215174309e7c6d91f9781176eff1e51c8b6746568d5f",
    "SourceLength": 5356,
    "SourceTimestampUtc": "2025-12-23T13:33:24.8088672Z",
    "LastIngestedUtc": "2025-12-23T13:33:35.154326Z"
  },
  {
    "Hostname": "BOYO-A05-AS-55",
    "ActualHostname": "BOYO-A05-AS-55",
    "Site": "BOYO",
    "FileHash": "b760108cb8b1654b630b18271cefb958dcd5ade21959685ccf68527a4bb17df8",
    "SourceLength": 5356,
    "SourceTimestampUtc": "2025-12-23T13:33:24.8541145Z",
    "LastIngestedUtc": "2025-12-23T13:33:35.3015912Z"
  }
]
