{
  "GeneratedAtUtc": "2026-01-03T01:27:23.2178323Z",
  "FilesAnalyzed": "C:\\Users\\Werem\\AppData\\Local\\Temp\\1d52ba37-4fb6-45d0-acac-76f8a0afe919\\metrics-missing-report.json",
  "TotalLaunchEvents": 0,
  "UniqueSites": 0,
  "DurationSeconds": null,
  "MaxObservedStreak": 0,
  "MaxAllowedStreak": 8,
  "SiteSummaries": [],
  "Violations": [],
  "ViolationCount": 0,
  "Pass": true,
  "Metrics": {
    "QueuedSites": {
      "Name": "QueuedSites",
      "Count": 0,
      "Min": null,
      "Average": null,
      "P50": null,
      "P95": null,
      "Max": null
    },
    "ActiveWorkers": {
      "Name": "ActiveWorkers",
      "Count": 0,
      "Min": null,
      "Average": null,
      "P50": null,
      "P95": null,
      "Max": null
    },
    "QueuedJobs": {
      "Name": "QueuedJobs",
      "Count": 0,
      "Min": null,
      "Average": null,
      "P50": null,
      "P95": null,
      "Max": null
    },
    "ThreadBudget": {
      "Name": "ThreadBudget",
      "Count": 0,
      "Min": null,
      "Average": null,
      "P50": null,
      "P95": null,
      "Max": null
    },
    "ActiveSites": {
      "Name": "ActiveSites",
      "Count": 0,
      "Min": null,
      "Average": null,
      "P50": null,
      "P95": null,
      "Max": null
    }
  }
}
