{
  "MetricsFile": "C:\\Users\\Werem\\Projects\\StateTrace\\Logs\\IngestionMetrics\\2025-12-26.json",
  "GeneratedAtUtc": "2025-12-26T22:41:39.2454625Z",
  "EvaluationWindowStartUtc": null,
  "EvaluationWindowEndUtc": null,
  "MaxAllowedConsecutive": 8,
  "EvaluationEnd": "2025-12-26T20:01:49.6308987Z",
  "TerminalSite": "WLLS",
  "SitesRemainingWhenStopped": 1,
  "PortBatchReadyCount": 3663,
  "EvaluatedPortBatchReadyCount": 2220,
  "UsedSynthesizedEvents": true,
  "IgnoredSynthesizedEvents": false,
  "ManualOverridesApplied": null,
  "ConcurrencyProfile": null,
  "RawAutoConcurrencyMode": false,
  "ObservedPortBatchReadyCount": 1443,
  "SynthesizedPortBatchReadyCount": 2220,
  "ParseEventCount": 7621,
  "SkippedDuplicateCount": 1036,
  "SiteStreaks": [
    {
      "Site": "BOYO",
      "MaxCount": 15,
      "StartTime": "2025-12-26T16:34:21.959185Z",
      "EndTime": "2025-12-26T16:34:55.567015Z",
      "HostSample": "BOYO-A05-AS-25"
    },
    {
      "Site": "WLLS",
      "MaxCount": 15,
      "StartTime": "2025-12-26T16:34:19.8538425Z",
      "EndTime": "2025-12-26T16:34:20.0638634Z",
      "HostSample": "WLLS-A01-AS-21"
    }
  ],
  "MaxStreakSegment": {
    "Site": "WLLS",
    "Count": 15,
    "StartTime": "2025-12-26T16:34:19.8538425Z",
    "EndTime": "2025-12-26T16:34:20.0638634Z",
    "StartIndex": 0,
    "EndIndex": 14,
    "HostSample": "WLLS-A01-AS-21",
    "HostSequenceSample": "WLLS-A01-AS-21, WLLS-A01-AS-21, WLLS-A01-AS-21, WLLS-A01-AS-21, WLLS-A01-AS-21, WLLS-A01-AS-21, WLLS-A01-AS-21, WLLS-A01-AS-21, WLLS-A01-AS-21, WLLS-A01-AS-21, WLLS-A01-AS-21, WLLS-A01-AS-21"
  }
}
